_pyseing.cpython-38-x86_64-linux-gnu.so
pyseing/__init__.py
pyseing/fp_calc.py
pyseing-0.1.1.dist-info/METADATA
pyseing-0.1.1.dist-info/WHEEL
pyseing-0.1.1.dist-info/top_level.txt
pyseing-0.1.1.dist-info/RECORD
