Metadata-Version: 2.1
Name: pyseing
Version: 0.1.1
Summary: SEING is a C/C++ package for fingerprint calculations suitable for machine learning studies of molecular systems.
Home-page: UNKNOWN
Author: Mardochee Reveil
Author-email: <mr937@cornell.edu>
License: UNKNOWN
Platform: UNKNOWN
